MANIFEST.in
README.rst
setup.py
src/digimat/__init__.py
src/digimat.tsdata.egg-info/PKG-INFO
src/digimat.tsdata.egg-info/SOURCES.txt
src/digimat.tsdata.egg-info/dependency_links.txt
src/digimat.tsdata.egg-info/namespace_packages.txt
src/digimat.tsdata.egg-info/not-zip-safe
src/digimat.tsdata.egg-info/requires.txt
src/digimat.tsdata.egg-info/top_level.txt
src/digimat/tsdata/__init__.py
src/digimat/tsdata/__main__.py
src/digimat/tsdata/tsdata.py